[
    {
        "title": "Vivo_V9 Pouch Case - Floral Soft Back Cover Case",
        "reviews": [
            "No Ratings"
        ],
        "full_price": null,
        "sale_price": null,
        "discount": null,
        "breadcrumbs": [],
        "brand": "No Brand",
        "is_available": "Out of stock",
        "seller_info": [],
        "seller": {
            "name": null,
            "store_url": null
        },
        "seller_rating": {
            "total": null,
            "details": []
        }
    },
    {
        "title": "Samsung A30S Pouch Cover - Love Soft Back Cover Case for Samsung A30S",
        "reviews": [
            "No Ratings"
        ],
        "full_price": null,
        "sale_price": null,
        "discount": null,
        "breadcrumbs": [],
        "brand": "No Brand",
        "is_available": "Out of stock",
        "seller_info": [],
        "seller": {
            "name": null,
            "store_url": null
        },
        "seller_rating": {
            "total": null,
            "details": []
        }
    },
    {
        "title": "Selfie Stick",
        "reviews": [
            "No Ratings"
        ],
        "full_price": null,
        "sale_price": null,
        "discount": null,
        "breadcrumbs": [],
        "brand": "No Brand",
        "is_available": "Out of stock",
        "seller_info": [],
        "seller": {
            "name": null,
            "store_url": null
        },
        "seller_rating": {
            "total": null,
            "details": []
        }
    },
    {
        "title": "Pack of 2 Butterfly wall stickers LED lights",
        "reviews": [
            "No Ratings"
        ],
        "full_price": null,
        "sale_price": null,
        "discount": null,
        "breadcrumbs": [],
        "brand": "No Brand",
        "is_available": "Out of stock",
        "seller_info": [],
        "seller": {
            "name": null,
            "store_url": null
        },
        "seller_rating": {
            "total": null,
            "details": []
        }
    },
    {
        "title": "pack of 2- Sketch Pad A3 & A4 Size sketching pad sketch book",
        "reviews": [
            "No Ratings"
        ],
        "full_price": null,
        "sale_price": null,
        "discount": null,
        "breadcrumbs": [],
        "brand": "No Brand",
        "is_available": "Out of stock",
        "seller_info": [],
        "seller": {
            "name": null,
            "store_url": null
        },
        "seller_rating": {
            "total": null,
            "details": []
        }
    },
    {
        "title": "Shams Al Emarat Khususi Perfume for Unisex - 100ml",
        "reviews": [
            "No Ratings"
        ],
        "full_price": null,
        "sale_price": null,
        "discount": null,
        "breadcrumbs": [],
        "brand": "Ard Al Zaafaran",
        "is_available": "Out of stock",
        "seller_info": [],
        "seller": {
            "name": null,
            "store_url": null
        },
        "seller_rating": {
            "total": null,
            "details": []
        }
    },
    {
        "title": "Huawei Y9s 2019 With Ring Holder GKK Full Coverage 360 Protection Mobile Phone Back Cover Case - Blue & Black",
        "reviews": [
            "No Ratings"
        ],
        "full_price": null,
        "sale_price": null,
        "discount": null,
        "breadcrumbs": [],
        "brand": "No Brand",
        "is_available": "Out of stock",
        "seller_info": [],
        "seller": {
            "name": null,
            "store_url": null
        },
        "seller_rating": {
            "total": null,
            "details": []
        }
    },
    {
        "title": "Samsung Galaxy S20 Plus Cover - SkinLee HQ Hard Case - Danaerys Dragon Queen GOT - SKINLEE-604-1-622-444",
        "reviews": [
            "No Ratings"
        ],
        "full_price": null,
        "sale_price": null,
        "discount": null,
        "breadcrumbs": [],
        "brand": "No Brand",
        "is_available": "Out of stock",
        "seller_info": [],
        "seller": {
            "name": null,
            "store_url": null
        },
        "seller_rating": {
            "total": null,
            "details": []
        }
    },
    {
        "title": "3 Bundles  of Pack of 50 Small Sticks For Art Craft Work (150 Sticks)",
        "reviews": [
            "No Ratings"
        ],
        "full_price": null,
        "sale_price": null,
        "discount": null,
        "breadcrumbs": [],
        "brand": "No Brand",
        "is_available": "Out of stock",
        "seller_info": [],
        "seller": {
            "name": null,
            "store_url": null
        },
        "seller_rating": {
            "total": null,
            "details": []
        }
    }
]